hamptt/__init__.py
hamptt/boards/__init__.py
hamptt/boards/abstptt.py
hamptt/boards/btptt.py
hamptt/boards/gpiobtt.py
hamptt/pttchooser.py
hamptt/utils.py
hamptt-0.3.1.dist-info/LICENSE.md
hamptt-0.3.1.dist-info/WHEEL
hamptt-0.3.1.dist-info/METADATA
hamptt-0.3.1.dist-info/RECORD
