Metadata-Version: 2.1
Name: hamptt
Version: 0.3.1
Summary: Implementation of Push-To-Talk board for ham radio transmitters like Baofeng UV-5R
Home-page: https://github.com/mrkeuz/hamptt/
License: MIT
Author: mrkeuz
Author-email: mr.keuz@ya.ru
Requires-Python: >=3.8,<4.0
Classifier: Development Status :: 3 - Alpha
Classifier: License :: OSI Approved :: MIT License
Classifier: Programming Language :: Python
Classifier: Programming Language :: Python :: 3
Classifier: Programming Language :: Python :: 3 :: Only
Classifier: Programming Language :: Python :: 3.8
Classifier: Programming Language :: Python :: 3.9
Classifier: Topic :: Communications :: Ham Radio
Classifier: Topic :: Utilities
Provides-Extra: bt
Requires-Dist: PyBluez (>=0.23); extra == "bt"
Requires-Dist: func_timeout (>=4.3.5)
Project-URL: Documentation, https://github.com/mrkeuz/hamptt/
